odoo/addons/accounting_partner_category/README.rst
odoo/addons/accounting_partner_category/__init__.py
odoo/addons/accounting_partner_category/__manifest__.py
odoo/addons/accounting_partner_category/i18n/accounting_partner_category.pot
odoo/addons/accounting_partner_category/i18n/es.po
odoo/addons/accounting_partner_category/i18n/fr.po
odoo/addons/accounting_partner_category/i18n/it.po
odoo/addons/accounting_partner_category/models/__init__.py
odoo/addons/accounting_partner_category/models/account_move.py
odoo/addons/accounting_partner_category/models/accounting_partner_category.py
odoo/addons/accounting_partner_category/models/res_partner.py
odoo/addons/accounting_partner_category/readme/CONFIGURATION.rst
odoo/addons/accounting_partner_category/readme/CONTRIBUTORS.rst
odoo/addons/accounting_partner_category/readme/DESCRIPTION.rst
odoo/addons/accounting_partner_category/readme/USAGE.rst
odoo/addons/accounting_partner_category/security/ir.model.access.csv
odoo/addons/accounting_partner_category/static/description/accounting_partner_category.png
odoo/addons/accounting_partner_category/static/description/company_accounting_partner_category.png
odoo/addons/accounting_partner_category/static/description/filters_invoice_contains_tag1_accounting_partner_category.png
odoo/addons/accounting_partner_category/static/description/filters_invoice_contains_tag1_without_tags2_accounting_partner_category.png
odoo/addons/accounting_partner_category/static/description/filters_invoice_without_tags2_accounting_partner_category.png
odoo/addons/accounting_partner_category/static/description/icon.png
odoo/addons/accounting_partner_category/static/description/index.html
odoo/addons/accounting_partner_category/static/description/invoice_with_accounting_partner_category.png
odoo/addons/accounting_partner_category/static/description/without_filters_accounting_partner_category.png
odoo/addons/accounting_partner_category/tests/__init__.py
odoo14_addon_accounting_partner_category-14.0.1.0.1.dev10.dist-info/METADATA
odoo14_addon_accounting_partner_category-14.0.1.0.1.dev10.dist-info/WHEEL
odoo14_addon_accounting_partner_category-14.0.1.0.1.dev10.dist-info/top_level.txt
odoo14_addon_accounting_partner_category-14.0.1.0.1.dev10.dist-info/RECORD
